{
    "paintings": [
        {
            "name": "nyarray_packs_m3oloqoy:000",
            "x": 48,
            "y": 64
        },
        {
            "name": "nyarray_packs_m3oloqoy:001",
            "x": 48,
            "y": 64
        },
        {
            "name": "nyarray_packs_m3oloqoy:002",
            "x": 36,
            "y": 48
        },
        {
            "name": "nyarray_packs_m3oloqoy:003",
            "x": 36,
            "y": 48
        },
        {
            "name": "nyarray_packs_m3oloqoy:004",
            "x": 36,
            "y": 48
        },
        {
            "name": "nyarray_packs_m3oloqoy:005",
            "x": 36,
            "y": 48
        },
        {
            "name": "nyarray_packs_m3oloqoy:006",
            "x": 36,
            "y": 48
        },
        {
            "name": "nyarray_packs_m3oloqoy:007",
            "x": 36,
            "y": 48
        },
        {
            "name": "nyarray_packs_m3oloqoy:008",
            "x": 36,
            "y": 48
        },
        {
            "name": "nyarray_packs_m3oloqoy:009",
            "x": 36,
            "y": 48
        },
        {
            "name": "nyarray_packs_m3oloqoy:010",
            "x": 36,
            "y": 48
        },
        {
            "name": "nyarray_packs_m3oloqoy:011",
            "x": 36,
            "y": 48
        },
        {
            "name": "nyarray_packs_m3oloqoy:012",
            "x": 36,
            "y": 48
        },
        {
            "name": "nyarray_packs_m3oloqoy:013",
            "x": 36,
            "y": 48
        },
        {
            "name": "nyarray_packs_m3oloqoy:014",
            "x": 36,
            "y": 48
        },
        {
            "name": "nyarray_packs_m3oloqoy:015",
            "x": 36,
            "y": 48
        },
        {
            "name": "nyarray_packs_m3oloqoy:016",
            "x": 36,
            "y": 48
        },
        {
            "name": "nyarray_packs_m3oloqoy:017",
            "x": 36,
            "y": 48
        },
        {
            "name": "nyarray_packs_m3oloqoy:018",
            "x": 36,
            "y": 48
        },
        {
            "name": "nyarray_packs_m3oloqoy:019",
            "x": 36,
            "y": 48
        },
        {
            "name": "nyarray_packs_m3oloqoy:020",
            "x": 36,
            "y": 48
        },
        {
            "name": "nyarray_packs_m3oloqoy:021",
            "x": 36,
            "y": 48
        },
        {
            "name": "nyarray_packs_m3oloqoy:022",
            "x": 36,
            "y": 48
        },
        {
            "name": "nyarray_packs_m3oloqoy:023",
            "x": 36,
            "y": 48
        },
        {
            "name": "nyarray_packs_m3oloqoy:024",
            "x": 36,
            "y": 48
        },
        {
            "name": "nyarray_packs_m3oloqoy:025",
            "x": 36,
            "y": 48
        },
        {
            "name": "nyarray_packs_m3oloqoy:026",
            "x": 36,
            "y": 48
        },
        {
            "name": "nyarray_packs_m3oloqoy:027",
            "x": 36,
            "y": 48
        },
        {
            "name": "nyarray_packs_m3oloqoy:028",
            "x": 36,
            "y": 48
        },
        {
            "name": "nyarray_packs_m3oloqoy:029",
            "x": 36,
            "y": 48
        }
    ]
}